audioop/__init__.pyi
audioop/_audioop.abi3.so
audioop/__init__.py
audioop/py.typed
audioop_lts-0.2.0.dist-info/RECORD
audioop_lts-0.2.0.dist-info/LICENSE
audioop_lts-0.2.0.dist-info/WHEEL
audioop_lts-0.2.0.dist-info/top_level.txt
audioop_lts-0.2.0.dist-info/METADATA
