Metadata-Version: 2.1
Name: audioop-lts
Version: 0.2.0
Summary: LTS Port of Python audioop
Maintainer-email: AbstractUmbra <umbra@abstractumbra.dev>
License: PSF-2.0
Project-URL: Homepage, https://github.com/AbstractUmbra/audioop
Classifier: Development Status :: 4 - Beta
Classifier: Intended Audience :: Developers
Classifier: Natural Language :: English
Classifier: Operating System :: OS Independent
Classifier: Programming Language :: Python :: 3.13
Classifier: Programming Language :: Python :: Implementation :: CPython
Requires-Python: >=3.13
License-File: LICENSE
